bin/Clock.py
bin/Log.py
bin/Parameters.py
bin/Primer.py
bin/Product.py
bin/__init__.py
bin/getCandidateKmers.py
bin/getPrimerPairs.py
bin/main.py
bin/removeOutgroupPrimers.py
bin/sortPrimerPairs.py
bin/validatePrimers.py
primerforge-1.5.3.dist-info/LICENSE
primerforge-1.5.3.dist-info/METADATA
primerforge-1.5.3.dist-info/WHEEL
primerforge-1.5.3.dist-info/entry_points.txt
primerforge-1.5.3.dist-info/top_level.txt
primerforge-1.5.3.dist-info/RECORD
