Metadata-Version: 2.1
Name: primerforge
Version: 1.5.3
Summary: software to identify primers that can be used to distinguish genomes
Author: Joseph S. Wirth
Classifier: Programming Language :: Python :: 3.11
Classifier: License :: OSI Approved :: MIT License
Classifier: Operating System :: OS Independent
Requires-Python: >=3.9,<3.12
License-File: LICENSE
Requires-Dist: biopython==1.81
Requires-Dist: khmer>=2.1
Requires-Dist: numpy
Requires-Dist: primer3-py>=2.0
Requires-Dist: pyahocorasick>=2.1
Requires-Dist: scipy>=1.10
